ntnx_lcm_py_client/__init__.py
ntnx_lcm_py_client/api_client.py
ntnx_lcm_py_client/api_response.py
ntnx_lcm_py_client/configuration.py
ntnx_lcm_py_client/rest.py
ntnx_lcm_py_client/Ntnx/__init__.py
ntnx_lcm_py_client/Ntnx/OneOfcommon/__init__.py
ntnx_lcm_py_client/Ntnx/OneOfcommon/v1/__init__.py
ntnx_lcm_py_client/Ntnx/OneOfcommon/v1/config/KVPairvalue.py
ntnx_lcm_py_client/Ntnx/OneOfcommon/v1/config/__init__.py
ntnx_lcm_py_client/Ntnx/OneOflcm/__init__.py
ntnx_lcm_py_client/Ntnx/OneOflcm/v4/__init__.py
ntnx_lcm_py_client/Ntnx/OneOflcm/v4/error/ErrorResponseerror.py
ntnx_lcm_py_client/Ntnx/OneOflcm/v4/error/__init__.py
ntnx_lcm_py_client/Ntnx/OneOflcm/v4/operations/CancelUpdateApiResponsedata.py
ntnx_lcm_py_client/Ntnx/OneOflcm/v4/operations/GetDownloadApiResponsedata.py
ntnx_lcm_py_client/Ntnx/OneOflcm/v4/operations/InventoryApiResponsedata.py
ntnx_lcm_py_client/Ntnx/OneOflcm/v4/operations/PrecheckApiResponsedata.py
ntnx_lcm_py_client/Ntnx/OneOflcm/v4/operations/UpdateApiResponsedata.py
ntnx_lcm_py_client/Ntnx/OneOflcm/v4/operations/__init__.py
ntnx_lcm_py_client/Ntnx/OneOflcm/v4/resources/DelBundleApiResponsedata.py
ntnx_lcm_py_client/Ntnx/OneOflcm/v4/resources/GenUpgradeNotifApiResponsedata.py
ntnx_lcm_py_client/Ntnx/OneOflcm/v4/resources/GenUpgradePlanApiResponsedata.py
ntnx_lcm_py_client/Ntnx/OneOflcm/v4/resources/GetBundleInfoApiResponsedata.py
ntnx_lcm_py_client/Ntnx/OneOflcm/v4/resources/GetBundlesApiResponsedata.py
ntnx_lcm_py_client/Ntnx/OneOflcm/v4/resources/GetEntitiesApiResponsedata.py
ntnx_lcm_py_client/Ntnx/OneOflcm/v4/resources/GetEntityApiResponsedata.py
ntnx_lcm_py_client/Ntnx/OneOflcm/v4/resources/GetHistoryApiResponsedata.py
ntnx_lcm_py_client/Ntnx/OneOflcm/v4/resources/GetHistoryByUuidApiResponsedata.py
ntnx_lcm_py_client/Ntnx/OneOflcm/v4/resources/GetImagesApiResponsedata.py
ntnx_lcm_py_client/Ntnx/OneOflcm/v4/resources/GetLcmConfigApiResponsedata.py
ntnx_lcm_py_client/Ntnx/OneOflcm/v4/resources/GetLcmStatusApiResponsedata.py
ntnx_lcm_py_client-4.0.1a1.dist-info/LICENSE.txt
ntnx_lcm_py_client-4.0.1a1.dist-info/METADATA
ntnx_lcm_py_client-4.0.1a1.dist-info/WHEEL
ntnx_lcm_py_client-4.0.1a1.dist-info/top_level.txt
ntnx_lcm_py_client-4.0.1a1.dist-info/RECORD
