Metadata-Version: 2.1
Name: ntnx-lcm-py-client
Version: 4.0.1a1
Summary: Nutanix Lcm Versioned APIs
Home-page: 
Author-email: sdk@nutanix.com
Keywords: Nutanix,v4,SDK,Nutanix Lcm Versioned APIs
License-File: LICENSE.txt
